{
        "sectionLabel": "Student details",
        "titleLabel": "Title",
        "familyNameLabel": "Family name",
        "familyNamePlaceholder": "Please enter family name",
        "familyNameError": "Please enter a valid family name",
        "givenNameLabel": "Given name(s)",
        "givenNamePlaceholder": "Please enter given name",
        "givenNameError": "Please enter a valid given name",
        "genderLabel": "Gender",
        "genderError": "Please select student's gender",
        "dobLabel": "Date of birth",
        "dobError": "Please enter a valid date of birth in the format DD/MM/YYYY",
        "dobDDPlaceholder": "DD",
        "dobMMPlaceholder": "MM",
        "dobYYYYPlaceholder": "YYYY",
        "nationalityLabel": "Nationality",
        "nationalityPlaceholder": "Nationality",
        "nationalityError": "Please select student's nationality from the list",
        "dualCitizenshipLabel": "Dual citizenship?",
        "dualCitizenshipError": "Please select if the student has dual citizenship",
        "dualCitizenshipCountryLabel": "Dual / second country of citizenship",
        "dualCitizenshipCountryPlaceholder": "Dual / second country of citizenship",
        "dualCitizenshipCountryError": "Please select a country from the list",
        "countryOfBirthLabel": "Country of birth",
        "countryOfBirthPlaceholder": "Country of birth",
        "countryOfBirthError": "Please select the student's country of birth",
        "addressLine1Label": "Address line 1",
        "addressLine1Placeholder": "Student's address line one",
        "addressLine1Error": "Please enter the first line of the student's address",
        "addressLine2Label": "Address line 2",
        "addressLine2Placeholder": "Student's address line two",
        "cityLabel": "City",
        "cityPlaceholder": "Please enter the city",
        "stateLabel": "State/Province",
        "statePlaceholder": "State/Province",
        "countryLabel": "Country",
        "countryPlaceholder": "Country",
        "countryError": "Please select a country from the list",
        "postalLabel": "Postcode / zip code",
        "postalPlaceholder": "Postcode / zip code",
        "postalError": "Please enter a Postcode / zip code",
        "livesAtAddressLabel": "Does student currently live at this address?",
        "livesAtAddressError": "Please select if the student lives at this address",
        "altAddressLine1Label": "Current address line 1",
        "altAddressLine1Placeholder": "Student's current address line one",
        "altAddressLine1Error": "Please the first line of the student's current address",
        "altAddressLine2Label": "Current address line 2",
        "altAddressLine2Placeholder": "Student's current address line two",
        "altCityLabel": "Current city",
        "altCityPlaceholder": "Please enter the current city",
        "altStateLabel": "State/Province",
        "altStatePlaceholder": "State/Province",
        "altCountryLabel": "Current country",
        "altCountryPlaceholder": "Please select a country from the list",
        "altCountryError": "Please select a country from the list",
        "altPostalLabel": "Current postcode / zip code",
        "altPostalPlaceholder": "Current postcode / zip code",
        "altPostalError": "Please enter a Postcode / zip code",
        "minimumAgeError": "Applicant must be at least {{placeholder}} years old",
        "weChatIdLabel": "WeChat ID",
        "weChatIdPlaceholder": "WeChat ID",
        "weChatIdError": "WeChatId must be less than 100 characters",
        "isStudentAustralianAboriginalOrTorresStraitIslander": "Is the student an Australian Aboriginal or Torres Strait Islander?",
        "doesStudentHaveRelativesLivingInAustralia": "Does the student have any relatives living in Australia (outside Perth)?",
        "doesStudentHaveRelativesLivingInPerth": "Does the student have any relatives living in Perth?",
        "relativesCityLabel": "Please specify the city",
        "relativesCityPlaceholder": "Please specify the city",
        "relativesCityError": "Please enter the relatives city"
}